pytca/__init__.py
pytca/analysis/__init__.py
pytca/analysis/bonds/__init__.py
pytca/analysis/bonds/bond_metrics.py
pytca/analysis/commodities/__init__.py
pytca/analysis/commodities/commodity_metrics.py
pytca/analysis/crypto/__init__.py
pytca/analysis/crypto/crypto_metrics.py
pytca/analysis/crypto/defi_tools.py
pytca/analysis/equities/__init__.py
pytca/analysis/equities/equity_metrics.py
pytca/analysis/fx/__init__.py
pytca/analysis/fx/fx_metrics.py
pytca/analysis/general/__init__.py
pytca/analysis/general/impact.py
pytca/analysis/general/metrics.py
pytca/analysis/geospatial/__init__.py
pytca/analysis/geospatial/geospatial.py
pytca/analysis/real_estate/__init__.py
pytca/analysis/real_estate/real_estate_metrics.py
pytca/analysis/sentiment/__init__.py
pytca/analysis/sentiment/sentiment_analysis.py
pytca/data/__init__.py
pytca/data/api_integration.py
pytca/data/loaders/__init__.py
pytca/data/loaders/arctic_loader.py
pytca/data/loaders/csv_loader.py
pytca/data/loaders/kdb_loader.py
pytca/data/loaders/mysql_loader.py
pytca/data/loaders/oracle_loader.py
pytca/data/loaders/pgsql_loader.py
pytca/data/loaders/sqlserver_loader.py
pytca/ml/__init__.py
pytca/ml/models.py
pytca/portfolio/__init__.py
pytca/portfolio/optimization.py
pytca/risk/__init__.py
pytca/risk/compliance.py
pytca/visualization/3d_visuals.py
pytca/visualization/__init__.py
pytca/visualization/bokeh_visuals.py
pytca/visualization/dash_app.py
pytca/visualization/plotly_visuals.py
pytca/visualization/plotter.py
test/__init__.py
test/test_analysis.py
test/test_data_loaders.py
test/test_ml.py
test/test_portfolio.py
test/test_risk.py
test/test_visualization.py
pytca-1.2.2.dist-info/LICENSE
pytca-1.2.2.dist-info/METADATA
pytca-1.2.2.dist-info/WHEEL
pytca-1.2.2.dist-info/top_level.txt
pytca-1.2.2.dist-info/RECORD
